widget_periodictable/__init__.py
widget_periodictable/utils.py
widget_periodictable/static/widget.css
widget_periodictable/static/widget.js
widget_periodictable-4.1.3.dist-info/METADATA
widget_periodictable-4.1.3.dist-info/WHEEL
widget_periodictable-4.1.3.dist-info/licenses/LICENSE.txt
widget_periodictable-4.1.3.dist-info/RECORD
