Metadata-Version: 2.3
Name: widget-periodictable
Version: 4.1.3
Summary: A jupyter widget of the periodic table of elements.
Project-URL: Home, https://www.osscar.org/
Project-URL: Source, https://github.com/osscar-org/widget-periodictable
Author: The OSSCAR team
License: BSD 3-Clause License
License-File: LICENSE.txt
Keywords: anywidget,jupyter,jupyterlab,mendeleev,osscar,widget
Classifier: Development Status :: 5 - Production/Stable
Classifier: Framework :: Jupyter
Classifier: Framework :: Jupyter :: JupyterLab
Classifier: Programming Language :: Python
Classifier: Programming Language :: Python :: 3.9
Classifier: Programming Language :: Python :: 3.10
Classifier: Programming Language :: Python :: 3.11
Classifier: Topic :: Scientific/Engineering
Requires-Python: >=3.9
Requires-Dist: anywidget~=0.9.10
Provides-Extra: dev
Requires-Dist: bumpver>=2023; extra == 'dev'
Requires-Dist: jupyterlab; extra == 'dev'
Requires-Dist: watchfiles; extra == 'dev'
